[
{
    "name": "CHONG Ming Lin Alice",
    "email": "alice.chong@cityu.edu.hk",
    "education": [
        "PhD., RSW, MH."
    ],
    "position": [
        "Former"
    ],
    "research interest": [
        "Social Gerontology",
        "Policy and Services for Older People in Chinese Societies",
        "Teaching & learning",
        "End of Life Issues",
        "Human Services Management"
    ],
    "image": "https://www.cityu.edu.hk/sites/g/files/asqsls3821/files/styles/crop_scholar_list_103_122/public/scholar/2_SS_CHONG_Ming_Lin_Alice_Photo_3.jpg?itok=zF2Arlzb"
}
]