[
{
    "name": "HUANG Hsu Wen",
    "email": "hwhuang@cityu.edu.hk",
    "education": [],
    "position": [
        "Assistant Professor,"
    ],
    "research interest": [
        "Language comprehension across the adult lifespan",
        "Visual word recognition",
        "Hemispheric asymmetry",
        "Event-related potentials (ERPs)"
    ],
    "image": "https://www.cityu.edu.hk/sites/g/files/asqsls3821/files/styles/crop_scholar_list_103_122/public/scholar/orcid_19.jpg?itok=g16ULTiJ"
}
]