[
{
    "name": "YIM Junhyok",
    "email": "j.yim@cityu.edu.hk",
    "education": [
        "Ph.D. - Organizational Behavior & Human Resource Management (Texas A&M University)\nMS - Management (Korea University)\nBA - Political Science & Business Administration (Korea University)"
    ],
    "position": [
        "Assistant Professor,"
    ],
    "research interest": [
        "Leadership",
        "Non-work to Work Interface",
        "Engagement",
        "Performance Management"
    ],
    "image": "https://www.cityu.edu.hk/sites/g/files/asqsls3821/files/styles/crop_scholar_list_103_122/public/scholar/_Picture_Junhyok_Yim_15.jpg?itok=suZc6n1M"
}
]