[
{
    "name": "ZENG Zhiyuan",
    "email": "zhiyzeng@cityu.edu.hk",
    "education": [
        "Postdoc Lawrence Berkeley National Laboratory\nPhD Nanyang Technological University\nMEng Zhejiang University\nBEng Central South Univeristy"
    ],
    "position": [
        "Assistant Professor,"
    ],
    "research interest": [
        "(1) Battery intercalation for material synthesis, mechanism study and energy applications",
        "(2) Failure mechanism study of Li-ion batteries using in-situ/ex-situ characterizations",
        "(3) Rational design of 2D transition metal dichalcogenides composites for HER",
        "(4) Fabrication of  transition metal based composites for environmental Applications"
    ],
    "image": "https://www.cityu.edu.hk/sites/g/files/asqsls3821/files/styles/crop_scholar_list_103_122/public/scholar/zhiyuan_zeng_61.jpg?itok=Ys1GwgqO"
}
]